ast_slizovskaia/__init__.py
ast_slizovskaia/ast_s.py
ast_slizovskaia/data/esc_means.npy
ast_slizovskaia/data/esc_std.npy
ast_slizovskaia/data/test_accuracy.png
ast_slizovskaia/dataset.py
ast_slizovskaia/hparams.py
ast_slizovskaia/model.py
ast_slizovskaia/train.py
ast_slizovskaia-0.1.4.dist-info/WHEEL
ast_slizovskaia-0.1.4.dist-info/METADATA
ast_slizovskaia-0.1.4.dist-info/RECORD
