Metadata-Version: 2.1
Name: ast-slizovskaia
Version: 0.1.4
Summary: Test exercise AST model on the ESC-50 dataset
Author: Olga Slizovskaia
Author-email: oslizovskaia@gmail.com
Requires-Python: >=3.8,<4.0
Classifier: Programming Language :: Python :: 3
Classifier: Programming Language :: Python :: 3.8
Classifier: Programming Language :: Python :: 3.9
Classifier: Programming Language :: Python :: 3.10
Requires-Dist: einops (>=0.4.1,<0.5.0)
Requires-Dist: librosa (>=0.9.2,<0.10.0)
Requires-Dist: numpy (>=1.21.0,<2.0.0)
Requires-Dist: pandas (>=1.4.4,<2.0.0)
Requires-Dist: pytorch-lightning (>=1.3.8,<2.0.0)
Requires-Dist: torchaudio (>=0.12.1,<0.13.0)
Requires-Dist: tqdm (>=4.61.2,<5.0.0)
